<level type="section">
  <num>31-734</num>
  <heading>Insurers rehabilitation and liquidation.</heading>
  <level>
    <num>(a)</num>
    <text>A mutual insurance holding company is deemed to be an insurer subject to Chapter 13 of this title, and shall automatically be a party to any proceeding under Chapter 13 of this title involving an insurance company, which as a result of a reorganization pursuant to § 31-731 or § 31-732 is a subsidiary of the mutual insurance holding company. In any proceeding under Chapter 13 of this title involving the reorganized insurance company, the assets of the mutual insurance holding company are deemed to be assets of the estate of the reorganized insurance company for purposes of satisfying the claims of the reorganized insurance company's policyholders.</text>
  </level>
  <level>
    <num>(b)</num>
    <text>A mutual insurance holding company shall not dissolve or liquidate without the approval of the Commissioner or as ordered by the District Court pursuant to Chapter 13 of this title.</text>
  </level>
  <level type="annotations">
    <level>
      <heading>History</heading>
      <text>(Sept. 20, 1996, D.C. Law 11-159, § 5, 43 DCR 3714; Mar. 24, 1998, D.C. Law 12-81, § 41(d), 45 DCR 745.)</text>
    </level>
    <level>
      <heading>Prior Codifications</heading>
      <text>1981 Ed., § 35-3724.</text>
    </level>
    <level>
      <heading>Emergency Legislation</heading>
      <text>See notes to § 35-3721.</text>
    </level>
    <level>
      <heading>Legislative History of Law 11-159</heading>
      <text>For legislative history of D.C. Law 11-159, see Historical and Statutory Notes following § 31-731.</text>
    </level>
    <level>
      <heading>Legislative History of Law 12-81</heading>
      <text>For legislative history of D.C. Law 12-81, see Historical and Statutory Notes following § 31-702.</text>
    </level>
  </level>
</level>
