<level type="section">
  <num>36-124</num>
  <heading>Refusal to surrender to registrant a registered container prima facie evidence of unlawful use.</heading>
  <formerly-cited-as>DC ST 1981 ยง 48-204</formerly-cited-as>
  <text>In any prosecution under this subchapter, the refusal of any person having possession of any registered milk bottle, can, crate, or other container to surrender possession of the same to the registrant of the name, mark, or device appearing thereon, after notice and demand by said registrant or his agent, shall be prima facie evidence of the unlawful use or traffic in the same contrary to the provisions of this subchapter.</text>
  <level>
    <type>annotations</type>
    <level>
      <heading>CREDIT(S)</heading>
      <text>(July 3, 1926, 44 Stat. 810, ch. 737, ยง 4.)</text>
    </level>
    <level>
      <heading>HISTORICAL AND STATUTORY NOTES</heading>
      <level>
        <heading>Prior Codifications</heading>
        <text>1981 Ed., ยง 48-204.</text>
        <text>1973 Ed., ยง 48-204.</text>
      </level>
    </level>
  </level>
</level>
