<level type="section">
  <num>31-759</num>
  <heading>Conversion of mutual insurance holding company.</heading>
  <text>Chapter 9 of this title shall be applicable to the conversion of a mutual insurance holding company formed under this subchapter to a stock company as if the mutual insurance holding company were a mutual insurance company.</text>
  <level type="annotations">
    <level>
      <heading>History</heading>
      <text>(May 12, 1998, D.C. Law 12-112, ยง 10, 45 DCR 1795.)</text>
    </level>
    <level>
      <heading>Prior Codifications</heading>
      <text>1981 Ed., ยง 35-3749.</text>
    </level>
    <level>
      <heading>Emergency Legislation</heading>
      <text>See Historical and Statutory Notes following ยง 31-751.</text>
    </level>
    <level>
      <heading>Legislative History of Law 12-112</heading>
      <text>For legislative history of D.C. Law 12-112, see Historical and Statutory Notes following ยง 31-751.</text>
    </level>
  </level>
</level>
