<level type="section">
  <num>4-1704.06</num>
  <heading>LRAP; disbursement of loans.</heading>
  <level>
    <num>(a)</num>
    <text>The Administrator shall begin to disburse loan repayment assistance within 90 days of the Administrator's receipt of adequate funds.</text>
  </level>
  <level>
    <num>(b)</num>
    <text>Subject to the availability of appropriations, loan repayment-assistance payments shall be made not less than semiannually to the participant until the repayment of the eligible debt is complete or the participant no longer meets the eligibility requirements set forth in § 4-1704.03.</text>
  </level>
  <level type="annotations">
    <level>
      <heading>History</heading>
      <text>(Sept. 24, 2010, D.C. Law 18-223, § 406, as added Sept. 14, 2011, D.C. Law 19-21, § 3002(b), 58 DCR 6226.)</text>
    </level>
    <level>
      <heading>Section References</heading>
      <text>This section is referenced in § 4-1704.04.</text>
    </level>
    <level>
      <heading>Legislative History of Law 19-21</heading>
      <text>For history of Law 19-21, see notes under § 4-1701.01.</text>
    </level>
  </level>
</level>
