<level type="section">
  <num>38-1702.05</num>
  <heading>Duties and responsibilities of charter schools.</heading>
  <text>Repealed.</text>
  <level type="annotations">
    <level>
      <heading>History</heading>
      <text>(May 29, 1996, D.C. Law 11-135, § 205, 43 DCR 1699; Oct. 19, 2000, D.C. Law 13-172, § 2802, 47 DCR 6308; Mar. 14, 2007, D.C. Law 16-268, § 3(c), 54 DCR 833; June 12, 2007, D.C. Law 17-9, § 803, 54 DCR 4102.)</text>
    </level>
    <level>
      <heading>Prior Codifications</heading>
      <text>1981 Ed., § 31-2815.</text>
    </level>
    <level>
      <heading>Emergency Legislation</heading>
      <text>For temporary (90-day) amendment of section, see § 2802 of the Fiscal Year 2001 Budget Support Emergency Act of 2000 (D.C. Act 13-376, July 24, 2000, 47 DCR 6574).</text>
      <text>For temporary (90 day) amendment of section, see § 2802 of the Fiscal Year 2001 Budget Support Congressional Review Emergency Act of 2000 (D.C. Act 13-438, October 20, 2000, 47 DCR 8740).</text>
    </level>
    <level>
      <heading>Legislative History of Law 11-135</heading>
      <text>For legislative history of D.C. Law 11-135, see Historical and Statutory Notes following § 38-1701.01.</text>
    </level>
    <level>
      <heading>Legislative History of Law 13-172</heading>
      <text>For Law 13-172, see notes following § 38-1702.02.</text>
    </level>
    <level>
      <heading>Legislative History of Law 16-268</heading>
      <text>For Law 16-268, see notes following § 38-1701.01.</text>
    </level>
    <level>
      <heading>Legislative History of Law 17-9</heading>
      <text>For Law 17-9, see notes following § 38-103.</text>
    </level>
  </level>
</level>
