<level type="section">
  <num>38-634</num>
  <heading>Rules and regulations for implementation of subchapter.</heading>
  <text>Repealed.</text>
  <level type="annotations">
    <level>
      <heading>History</heading>
      <text>(Oct. 5, 1993, D.C. Law 10-55, § 5, 40 DCR 7219; Feb. 2, 2008, D.C. Law 17-107, § 14, 54 DCR 12230.)</text>
    </level>
    <level>
      <heading>Prior Codifications</heading>
      <text>1981 Ed., § 31-2434.</text>
    </level>
    <level>
      <heading>Emergency Legislation</heading>
      <text>See notes to § 38-631.</text>
      <text>For temporary (90-day) addition of §§ 31-2451 to 31-2454 1981 Ed., see §§ 2 to 5 of the Attendance and School Safety Emergency Act of 2000 (D.C. Act 13-319, April 17, 2000, 47 DCR 2882).</text>
    </level>
    <level>
      <heading>Legislative History of Law 10-55</heading>
      <text>For legislative history of D.C. Law 10-55, see Historical and Statutory Notes following § 38-631.</text>
    </level>
    <level>
      <heading>Legislative History of Law 17-107</heading>
      <text>For Law 17-107, see notes following § 38-631.</text>
    </level>
  </level>
</level>
