<level type="section">
  <num>3-1206.52</num>
  <heading>License renewal.</heading>
  <text>The Board of Medicine shall renew the license of a trauma technologist who, in addition to meeting the requirements of ยง 3-1205.04(r), has submitted to the Board, along with an application for renewal, documentation of successful completion of 50 hours of Board-approved continuing medical education within 2 years before the date the license expires. Continuing medical education may consist of critiques, didactic session, practical drills, workshops, seminars, or other Board-approved means.</text>
  <level type="annotations">
    <level>
      <heading>History</heading>
      <text>(Mar. 25, 1986, D.C. Law 6-99, ยง 652, as added Jan. 25, 2014, D.C. Law 20-64, ยง 2(g), 60 DCR 16533.)</text>
    </level>
    <level>
      <heading>Effect of Amendments</heading>
      <text>The 2014 amendment by D.C. Law 20-64 added this section.</text>
    </level>
    <level>
      <heading>Legislative History of Law 20-64</heading>
      <text>See note to ยง 3-1201.02.</text>
    </level>
  </level>
</level>
