<level type="section">
  <num>47-318.05</num>
  <heading>Mayoral budget submissions required; accounting of expenditures - Cash flow statements.</heading>
  <text>The Mayor shall submit to the Council, beginning October 1, 1993, and every month thereafter, monthly consolidated cash flow statements in the same format as currently prepared by the Office of the D.C. Treasurer, except that the statement submitted to the Council shall contain an explanation of all changes in cash flows that have occurred since the previous month's report.</text>
  <level type="annotations">
    <level>
      <heading>History</heading>
      <text>(Nov. 25, 1993, D.C. Law 10-64, ยง 7, 40 DCR 7347; enacted, Apr. 9, 1997, D.C. Law 11-254, ยง 2, 44 DCR 1575.)</text>
    </level>
    <level>
      <heading>Prior Codifications</heading>
      <text>1981 Ed., ยง 47-318.5.</text>
    </level>
    <level>
      <heading>Legislative History of Law 10-64</heading>
      <text>For legislative history of D.C. Law 10-64, see Historical and Statutory Notes following ยง 47-318.</text>
    </level>
  </level>
</level>
