<level type="section">
  <num>7-651.07</num>
  <heading>Decision to resuscitate.</heading>
  <level>
    <num>(a)</num>
    <text>If EMS personnel encounter a patient who is in cardiac or respiratory arrest and the patient is wearing a comfort care bracelet or necklace that is intact or has not been defaced, but the patient, or the patient's authorized decision-maker or surrogate, orally requests that EMS personnel resuscitate the patient, EMS personnel shall resuscitate and the patient, or the patient's authorized decision-maker or surrogate, shall remove the comfort care bracelet or necklace from the patient to ensure that the revocation of the comfort care order is honored at the hospital.</text>
  </level>
  <level>
    <num>(b)</num>
    <text>If EMS personnel encounter a patient who is in cardiac or respiratory arrest and the patient is wearing a comfort care bracelet or necklace that is not intact or has been defaced, EMS personnel shall resuscitate. If there is a reason to question whether the comfort care bracelet or necklace is intact or has been defaced, EMS personnel shall resuscitate.</text>
  </level>
  <level>
    <type>annotations</type>
    <level>
      <heading>CREDIT(S)</heading>
      <text>(Apr. 3, 2001, D.C. Law 13-224, ยง 8, 48 DCR 27.)</text>
    </level>
    <level>
      <heading>HISTORICAL AND STATUTORY NOTES</heading>
      <level>
        <heading>Legislative History of Laws</heading>
        <text>For D.C. Law 13-224, see notes following ยง 7-651.01.</text>
      </level>
    </level>
  </level>
</level>
