<level type="section">
  <num>5-1501.07</num>
  <heading>Testing of breath alcohol equipment.</heading>
  <level>
    <num>(a)</num>
    <text>The Department shall test and certify, at least once every 3 months or as recommended by the manufacturer, whichever is more frequent, the accuracy of all equipment used by any District law enforcement personnel to test the alcohol content of breath.</text>
  </level>
  <level>
    <num>(b)</num>
    <text>Only equipment certified by the Department to be accurate shall be used by a District law enforcement agency to test the alcohol content of breath.</text>
  </level>
  <level>
    <num>(c)</num>
    <text>The Director may delegate by memorandum of agreement to the Office of the Chief Medical Examiner the responsibility for testing breath alcohol equipment and some or all of the responsibility for providing forensic science services pertaining to forensic alcohol.</text>
  </level>
  <level>
    <type>annotations</type>
    <level>
      <heading>CREDIT(S)</heading>
      <text>(Aug. 17, 2011, D.C. Law 19-18, ยง 8, 58 DCR 5403.)</text>
    </level>
    <level>
      <heading>HISTORICAL AND STATUTORY NOTES</heading>
      <level>
        <heading>Emergency Act Amendments</heading>
        <text>For temporary (90 day) amendment of section, see ยง 201 of Comprehensive Impaired Driving and Alcohol Testing Program Emergency Amendment Act of 2012 (D.C. Act 19-429, July 30, 2012, 59 DCR 9387).</text>
        <text>For temporary (90 day) amendment of section, see ยง 201 of Comprehensive Impaired Driving and Alcohol Testing Program Congressional Review Emergency Amendment Act of 2012 (D.C. Act 19-508, October 26, 2012, 59 DCR 12774).</text>
      </level>
      <level>
        <heading>Legislative History of Laws</heading>
        <text>For history of Law 19-18, see notes under ยง 5-1501.01.</text>
      </level>
    </level>
  </level>
</level>
