<level type="section">
  <num>47-398.03</num>
  <heading>No appropriation necessary for arena preconstruction activities.</heading>
  <text>The fourth sentence of section 446 of the District of Columbia Home Rule Act (§ 1-204.46) shall not apply with respect to any of the following obligations or expenditures:</text>
  <level>
    <num>(1)</num>
    <text>Borrowing conducted pursuant to § 47-398.01(a);</text>
  </level>
  <level>
    <num>(2)</num>
    <text>The pledging of revenues as security for such borrowing pursuant to § 47-398.02(a);</text>
  </level>
  <level>
    <num>(3)</num>
    <text>The payment of principal, interest, premium, debt servicing, contributions to reserves, or other costs associated with such borrowing; or</text>
  </level>
  <level>
    <num>(4)</num>
    <text>Other obligations or expenditures made to carry out any arena preconstruction activity described in § 47-398.04.</text>
  </level>
  <level type="annotations">
    <level>
      <heading>History</heading>
      <text>(Sept. 6, 1995, 109 Stat. 269, Pub. L. 104-28, § 203; enacted, Apr. 9, 1997, D.C. Law 11-254, § 2, 44 DCR 1575.)</text>
    </level>
    <level>
      <heading>Prior Codifications</heading>
      <text>1981 Ed., § 47-398.3.</text>
    </level>
  </level>
</level>
